<?xml version = '1.0' encoding = 'UTF-8'?>
<Diagram class="oracle.dbtools.crest.swingui.relational.DPVRelational" name="Relational_1" id="51B8354B-A874-A149-A0FE-718539AD46F6">
<createdBy>Aluno</createdBy>
<modifiedBy>Aluno</modifiedBy>
<createdTime>2022-04-19 23:24:27 UTC</createdTime>
<autoRoute>false</autoRoute>
<boxInbox>true</boxInbox>
<showLegend>false</showLegend>
<showLabels>false</showLabels>
<showRelAttributes>false</showRelAttributes>
<gridEnabled>false</gridEnabled>
<showGrid>false</showGrid>
<diagramColor>-1</diagramColor>
<display>false</display>
<notation>1</notation>
<objectViews>
<OView class="oracle.dbtools.crest.swingui.relational.TVTable" oid="A4136480-1E10-FE90-1394-1CEE69DEE95A" otype="Table" vid="C6C83A4C-0F15-7F44-5DEE-15B76FF62B30">
<hideElementsInCurrentOnly>false</hideElementsInCurrentOnly>
<bounds x="90" y="76" width="159" height="142"/>
</OView>
</objectViews>
</Diagram>
