<?xml version = '1.0' encoding = 'UTF-8'?>
<Diagram class="oracle.dbtools.crest.swingui.logical.DPVLogical" name="Logical" id="3D594312-89CA-38B1-70ED-280ED52C5FC1">
<createdBy>Aluno</createdBy>
<modifiedBy>Aluno</modifiedBy>
<createdTime>2022-04-19 23:08:25 UTC</createdTime>
<autoRoute>false</autoRoute>
<boxInbox>true</boxInbox>
<showLegend>false</showLegend>
<showLabels>false</showLabels>
<showRelAttributes>false</showRelAttributes>
<gridEnabled>false</gridEnabled>
<showGrid>false</showGrid>
<diagramColor>-1</diagramColor>
<display>false</display>
<notation>1</notation>
<objectViews>
<OView class="oracle.dbtools.crest.swingui.logical.TVEntity" oid="642029E6-FEEF-E990-51B6-BC01A4C9B95D" otype="Entity" vid="00D3D915-E6E4-5D3B-9C69-961293383A30">
<hideElementsInCurrentOnly>false</hideElementsInCurrentOnly>
<bounds x="47" y="54" width="159" height="142"/>
</OView>
</objectViews>
</Diagram>
